snail_print/__init__.py
snail_print/utils.py
snail_print-0.1.9.dist-info/LICENSE
snail_print-0.1.9.dist-info/WHEEL
snail_print-0.1.9.dist-info/METADATA
snail_print-0.1.9.dist-info/RECORD
