Metadata-Version: 2.1
Name: snail-print
Version: 0.1.9
Summary: A print funtion that slowly shows the output in console in real time
Home-page: https://github.com/Baelfire18/snail_print
License: MIT
Keywords: print,console,realtime,slowly
Author: Jose Antonio Castro
Author-email: jacastro18@uc.cl
Requires-Python: >=3.7,<4.0
Classifier: Environment :: Console
Classifier: Intended Audience :: Developers
Classifier: License :: OSI Approved :: MIT License
Classifier: Programming Language :: Python :: 3
Classifier: Programming Language :: Python :: 3.10
Classifier: Programming Language :: Python :: 3.7
Classifier: Programming Language :: Python :: 3.8
Classifier: Programming Language :: Python :: 3.9
Classifier: Topic :: Software Development :: Build Tools
Classifier: Topic :: Software Development :: Libraries :: Python Modules
Project-URL: Repository, https://github.com/Baelfire18/snail_print
